{"toil":{"songid":"toil","songname":"Nonstop Toil","albumid":"quarry","album":"From The Quarry","albumpos":1,"year":2020,"instrumental":true,"spotify":"","youtube":"https://youtu.be/NNrJnHprVcU","soundcloud":"","filePath":"audio/toil.mp3","coverPath":"img/icons/quarry.jpg","runtime":"1:36"},"tripwired2":{"songid":"tripwired2","songname":"Tripwired","albumid":"quarry","album":"From The Quarry","albumpos":2,"year":2020,"instrumental":false,"spotify":"","youtube":"https://youtu.be/rNJvG8KgjO0","soundcloud":"https://soundcloud.com/bensomerville/tripwired-q-edition","filePath":"audio/tripwired2.mp3","coverPath":"img/icons/quarry.jpg","runtime":"5:37"},"sorentino":{"songid":"sorentino","songname":"Sorentino","albumid":"quarry","album":"From The Quarry","albumpos":3,"year":2020,"instrumental":true,"spotify":"","youtube":"https://youtu.be/kklpb8LWkX8","soundcloud":"","filePath":"audio/sorentino.mp3","coverPath":"img/icons/quarry.jpg","runtime":"1:48"},"eastcoast":{"songid":"eastcoast","songname":"It's June On The East Coast Of Brazil","albumid":"eastcoast","album":"","albumpos":1,"year":2018,"instrumental":false,"spotify":"https://open.spotify.com/track/0bnme9xfqisaAirmbXC0rk?si=Pe8pf6inSDmy9JoXqH2uxQ","youtube":"https://youtu.be/HyGNdFQCy7M","soundcloud":"https://soundcloud.com/bensomerville/its-june-on-the-east-coast","filePath":"audio/eastcoast.mp3","coverPath":"img/icons/eastcoast.jpg","runtime":"4:57"},"tension":{"songid":"tension","songname":"The Tension","albumid":"entanglement","album":"Entanglement","albumpos":1,"year":2017,"instrumental":false,"spotify":"https://open.spotify.com/track/3kVfb3zxABzn4Z5YDjWCjQ?si=_OemQKkKQ2uUbvqR78sZwQ","youtube":"https://youtu.be/d5HfaiyunUM","soundcloud":"https://soundcloud.com/bensomerville/the-tension?in=bensomerville/sets/entanglement","filePath":"audio/tension.mp3","coverPath":"img/icons/entanglement.jpg","runtime":"3:56"},"diminishing":{"songid":"diminishing","songname":"Diminishing Eye","albumid":"entanglement","album":"Entanglement","albumpos":2,"year":2017,"instrumental":false,"spotify":"https://open.spotify.com/track/3sIXx9y0TBXfO1W8qugI7Q?si=hiHn_8cVTdO21bjjtxNy6Q","youtube":"https://youtu.be/B-KuEay5AiI","soundcloud":"https://soundcloud.com/bensomerville/diminishing-eye?in=bensomerville/sets/entanglement","filePath":"audio/diminishing.mp3","coverPath":"img/icons/entanglement.jpg","runtime":"3:15"},"stage":{"songid":"stage","songname":"The Stage","albumid":"entanglement","album":"Entanglement","albumpos":3,"year":2017,"instrumental":false,"spotify":"https://open.spotify.com/track/52NwXwTzViIpOXGBe6i606?si=8RuqAbgOQkGeO9YqQbpMIg","youtube":"https://youtu.be/EbsQynzM7eY","soundcloud":"https://soundcloud.com/bensomerville/the-stage?in=bensomerville/sets/entanglement","filePath":"audio/stage.mp3","coverPath":"img/icons/entanglement.jpg","runtime":"4:01"},"pullmeapart":{"songid":"pullmeapart","songname":"Pull Me Apart","albumid":"entanglement","album":"Entanglement","albumpos":4,"year":2017,"instrumental":false,"spotify":"https://open.spotify.com/track/4V2BXtOP4Z3tHVIfpvjwBE?si=JpDFiT5_ReSbtRkRxDdTZA","youtube":"https://youtu.be/qkOy3E85z9c","soundcloud":"https://soundcloud.com/bensomerville/pull-me-apart?in=bensomerville/sets/entanglement","filePath":"audio/pullmeapart.mp3","coverPath":"img/icons/entanglement.jpg","runtime":"3:45"},"rest":{"songid":"rest","songname":"Rest","albumid":"entanglement","album":"Entanglement","albumpos":5,"year":2017,"instrumental":false,"spotify":"https://open.spotify.com/track/2NcX2UOH4kJ5VXgTAC92Sw?si=0VGudAdORrSRsBbdCnHE7w","youtube":"https://youtu.be/gWHP4QruZ_o","soundcloud":"https://soundcloud.com/bensomerville/rest?in=bensomerville/sets/entanglement","filePath":"audio/rest.mp3","coverPath":"img/icons/entanglement.jpg","runtime":"3:11"},"mrforeigner":{"songid":"mrforeigner","songname":"Mr Foreigner","albumid":"entanglement","album":"Entanglement","albumpos":6,"year":2017,"instrumental":false,"spotify":"https://open.spotify.com/track/1x4wMCIv8taxNHRPjdIB57?si=bXTCvUUHRLCTOryU9YCfUQ","youtube":"https://youtu.be/QtP-pZH3-HU","soundcloud":"https://soundcloud.com/bensomerville/mr-foreigner?in=bensomerville/sets/entanglement","filePath":"audio/mrforeigner.mp3","coverPath":"img/icons/entanglement.jpg","runtime":"5:05"},"imaginarypain":{"songid":"imaginarypain","songname":"Imaginary Pain","albumid":"entanglement","album":"Entanglement","albumpos":7,"year":2017,"instrumental":false,"spotify":"https://open.spotify.com/track/3mkwbyCZYr9pi2DjkdbOr5?si=0orBySHpQnydIwVPS3r7PA","youtube":"https://youtu.be/UhoXqXqqzqE","soundcloud":"https://soundcloud.com/bensomerville/imaginary-pain?in=bensomerville/sets/entanglement","filePath":"audio/imaginarypain.mp3","coverPath":"img/icons/entanglement.jpg","runtime":"3:55"},"togive":{"songid":"togive","songname":"To Give Is To Love","albumid":"entanglement","album":"Entanglement","albumpos":8,"year":2017,"instrumental":false,"spotify":"https://open.spotify.com/track/0onZt7azFCsFaS3oePadoH?si=JmerK6XzTQqzQBC-gmLuww","youtube":"https://youtu.be/7OmZ5MA-MGg","soundcloud":"https://soundcloud.com/bensomerville/to-give-is-to-love?in=bensomerville/sets/entanglement","filePath":"audio/togive.mp3","coverPath":"img/icons/entanglement.jpg","runtime":"3:32"},"ithought":{"songid":"ithought","songname":"I Thought Too Much Of You","albumid":"entanglement","album":"Entanglement","albumpos":9,"year":2017,"instrumental":false,"spotify":"https://open.spotify.com/track/3ZxcA7LgmWeJ9PlfqTboQ4?si=ztDgdhJtQ16rQgrKhqg3eg","youtube":"https://youtu.be/45gC5LVNkR8","soundcloud":"https://soundcloud.com/bensomerville/i-thought-too-much-of-you?in=bensomerville/sets/entanglement","filePath":"audio/ithought.mp3","coverPath":"img/icons/entanglement.jpg","runtime":"3:47"},"father":{"songid":"father","songname":"FatherAwaken Us!","albumid":"entanglement","album":"Entanglement","albumpos":10,"year":2017,"instrumental":false,"spotify":"https://open.spotify.com/track/4kGWnrJRfkC5WA2n1tLF7s?si=WAn4LT2CQ8qlrsj0qi-8SA","youtube":"https://youtu.be/IyfYeEnUvVM","soundcloud":"https://soundcloud.com/bensomerville/father-awaken-us?in=bensomerville/sets/entanglement","filePath":"audio/father.mp3","coverPath":"img/icons/entanglement.jpg","runtime":"2:54"},"cyclopath":{"songid":"cyclopath","songname":"Cyclopath","albumid":"euw","album":"Ears Under Water","albumpos":1,"year":2016,"instrumental":false,"spotify":"","youtube":"","soundcloud":"","filePath":"audio/cyclopath.mp3","coverPath":"img/icons/euw.jpg","runtime":"5:02"},"srj":{"songid":"srj","songname":"Save Robert Jones","albumid":"euw","album":"Ears Under Water","albumpos":2,"year":2016,"instrumental":false,"spotify":"","youtube":"","soundcloud":"","filePath":"audio/srj.mp3","coverPath":"img/icons/euw.jpg","runtime":"3:30"},"topsong":{"songid":"topsong","songname":"Top Song","albumid":"euw","album":"Ears Under Water","albumpos":3,"year":2016,"instrumental":false,"spotify":"","youtube":"","soundcloud":"","filePath":"audio/topsong.mp3","coverPath":"img/icons/euw.jpg","runtime":"4:54"},"thatsano":{"songid":"thatsano","songname":"That's A No","albumid":"euw","album":"Ears Under Water","albumpos":4,"year":2016,"instrumental":false,"spotify":"","youtube":"","soundcloud":"","filePath":"audio/thatsano.mp3","coverPath":"img/icons/euw.jpg","runtime":"3:38"},"sirdoubts":{"songid":"sirdoubts","songname":"Sir Doubts","albumid":"euw","album":"Ears Under Water","albumpos":5,"year":2016,"instrumental":false,"spotify":"","youtube":"","soundcloud":"","filePath":"audio/sirdoubts.mp3","coverPath":"img/icons/euw.jpg","runtime":"3:07"},"changesomeone":{"songid":"changesomeone","songname":"Change Someone","albumid":"euw","album":"Ears Under Water","albumpos":6,"year":2016,"instrumental":false,"spotify":"","youtube":"","soundcloud":"","filePath":"audio/changesomeone.mp3","coverPath":"img/icons/euw.jpg","runtime":"3:42"},"fatedelay":{"songid":"fatedelay","songname":"Fate Delay","albumid":"euw","album":"Ears Under Water","albumpos":7,"year":2016,"instrumental":false,"spotify":"","youtube":"","soundcloud":"","filePath":"audio/fatedelay.mp3","coverPath":"img/icons/euw.jpg","runtime":"5:34"},"twoeyes":{"songid":"twoeyes","songname":"Read With Two Eyes","albumid":"euw","album":"Ears Under Water","albumpos":8,"year":2016,"instrumental":false,"spotify":"","youtube":"","soundcloud":"","filePath":"audio/twoeyes.mp3","coverPath":"img/icons/euw.jpg","runtime":"4:29"},"postal":{"songid":"postal","songname":"Postal","albumid":"euw","album":"Ears Under Water","albumpos":9,"year":2016,"instrumental":false,"spotify":"","youtube":"","soundcloud":"","filePath":"audio/postal.mp3","coverPath":"img/icons/euw.jpg","runtime":"4:19"},"wheelless":{"songid":"wheelless","songname":"Song For The Wheelless","albumid":"euw","album":"Ears Under Water","albumpos":10,"year":2016,"instrumental":false,"spotify":"","youtube":"","soundcloud":"","filePath":"audio/wheelless.mp3","coverPath":"img/icons/euw.jpg","runtime":"3:14"},"anystar":{"songid":"anystar","songname":"Any Star","albumid":"euw","album":"Ears Under Water","albumpos":11,"year":2016,"instrumental":false,"spotify":"","youtube":"","soundcloud":"","filePath":"audio/anystar.mp3","coverPath":"img/icons/euw.jpg","runtime":"4:45"},"regrouping":{"songid":"regrouping","songname":"Semi-Improvisation in E (A Regrouping)","albumid":"euw","album":"Ears Under Water","albumpos":12,"year":2016,"instrumental":true,"spotify":"","youtube":"","soundcloud":"","filePath":"audio/regrouping.mp3","coverPath":"img/icons/euw.jpg","runtime":"2:45"},"gb":{"songid":"gb","songname":"GB Pharmacy","albumid":"euw","album":"Ears Under Water","albumpos":13,"year":2016,"instrumental":false,"spotify":"","youtube":"","soundcloud":"","filePath":"audio/gb.mp3","coverPath":"img/icons/euw.jpg","runtime":"3:28"},"barcode":{"songid":"barcode","songname":"Barcode","albumid":"euw","album":"Ears Under Water","albumpos":14,"year":2016,"instrumental":false,"spotify":"","youtube":"","soundcloud":"","filePath":"audio/barcode.mp3","coverPath":"img/icons/euw.jpg","runtime":"5:55"},"hireamaid":{"songid":"hireamaid","songname":"Hire A Maid","albumid":"euw","album":"Ears Under Water","albumpos":15,"year":2016,"instrumental":false,"spotify":"","youtube":"","soundcloud":"","filePath":"audio/hireamaid.mp3","coverPath":"img/icons/euw.jpg","runtime":"4:02"},"stairs":{"songid":"stairs","songname":"10,000 Stairs","albumid":"euw","album":"Ears Under Water","albumpos":16,"year":2016,"instrumental":false,"spotify":"","youtube":"","soundcloud":"","filePath":"audio/stairs.mp3","coverPath":"img/icons/euw.jpg","runtime":"3:59"},"sandbridge":{"songid":"sandbridge","songname":"Sandbridge","albumid":"euw","album":"Ears Under Water","albumpos":17,"year":2016,"instrumental":true,"spotify":"","youtube":"","soundcloud":"","filePath":"audio/sandbridge.mp3","coverPath":"img/icons/euw.jpg","runtime":"4:00"},"patricians":{"songid":"patricians","songname":"The Patricians","albumid":"euw","album":"Ears Under Water","albumpos":18,"year":2016,"instrumental":false,"spotify":"","youtube":"","soundcloud":"","filePath":"audio/patricians.mp3","coverPath":"img/icons/euw.jpg","runtime":"5:05"},"contraspective":{"songid":"contraspective","songname":"Contraspective","albumid":"euw","album":"Ears Under Water","albumpos":19,"year":2016,"instrumental":false,"spotify":"","youtube":"","soundcloud":"","filePath":"audio/contraspective.mp3","coverPath":"img/icons/euw.jpg","runtime":"3:15"},"pretensent":{"songid":"pretensent","songname":"Pretensent","albumid":"euw","album":"Ears Under Water","albumpos":20,"year":2016,"instrumental":false,"spotify":"","youtube":"","soundcloud":"","filePath":"audio/pretensent.mp3","coverPath":"img/icons/euw.jpg","runtime":"2:45"},"whatexcuse":{"songid":"whatexcuse","songname":"What Excuse","albumid":"euw","album":"Ears Under Water","albumpos":21,"year":2016,"instrumental":false,"spotify":"","youtube":"","soundcloud":"","filePath":"audio/whatexcuse.mp3","coverPath":"img/icons/euw.jpg","runtime":"3:42"},"fortuneteller":{"songid":"fortuneteller","songname":"Fortune Teller","albumid":"euw","album":"Ears Under Water","albumpos":22,"year":2016,"instrumental":false,"spotify":"","youtube":"","soundcloud":"","filePath":"audio/fortuneteller.mp3","coverPath":"img/icons/euw.jpg","runtime":"3:04"},"backbend":{"songid":"backbend","songname":"Backbend","albumid":"euw","album":"Ears Under Water","albumpos":23,"year":2016,"instrumental":false,"spotify":"","youtube":"","soundcloud":"","filePath":"audio/backbend.mp3","coverPath":"img/icons/euw.jpg","runtime":"3:03"},"becky":{"songid":"becky","songname":"Becky","albumid":"euw","album":"Ears Under Water","albumpos":24,"year":2016,"instrumental":false,"spotify":"","youtube":"","soundcloud":"","filePath":"audio/becky.mp3","coverPath":"img/icons/euw.jpg","runtime":"2:53"},"sandbridge2":{"songid":"sandbridge2","songname":"Sandbridge (Reprise)","albumid":"euw","album":"Ears Under Water","albumpos":25,"year":2016,"instrumental":true,"spotify":"","youtube":"","soundcloud":"","filePath":"audio/sandbridge2.mp3","coverPath":"img/icons/euw.jpg","runtime":"3:56"},"earsunderwater":{"songid":"earsunderwater","songname":"Ears Under Water","albumid":"euw","album":"Ears Under Water","albumpos":26,"year":2016,"instrumental":true,"spotify":"","youtube":"","soundcloud":"","filePath":"audio/earsunderwater.mp3","coverPath":"img/icons/euw.jpg","runtime":"5:19"},"manna":{"songid":"manna","songname":"Manna","albumid":"greenstone","album":"The Greenstone EP","albumpos":1,"year":2015,"instrumental":false,"spotify":"https://open.spotify.com/track/3I1dHm2UsaVbamMCeWNf6K?si=xoluF99kSneUajcOfpq44Q","youtube":"https://youtu.be/35XT_lcPO1k","soundcloud":"https://soundcloud.com/bensomerville/manna?in=bensomerville/sets/the-greenstone-ep","filePath":"audio/manna.mp3","coverPath":"img/icons/greenstone.jpg","runtime":"4:05"},"counterprofeit":{"songid":"counterprofeit","songname":"Counterprofeit","albumid":"greenstone","album":"The Greenstone EP","albumpos":2,"year":2015,"instrumental":false,"spotify":"https://open.spotify.com/track/5V7mqYxTU8hsiOstQg6x8k?si=pdPq-ngcSJWYC_SpTtOjqA","youtube":"https://youtu.be/KadlpPb_rj0","soundcloud":"https://soundcloud.com/bensomerville/counterprofeit?in=bensomerville/sets/the-greenstone-ep","filePath":"audio/counterprofeit.mp3","coverPath":"img/icons/greenstone.jpg","runtime":"3:53"},"taxi":{"songid":"taxi","songname":"Taxintermission","albumid":"greenstone","album":"The Greenstone EP","albumpos":3,"year":2015,"instrumental":true,"spotify":"https://open.spotify.com/track/6dBx1wHglg5UjYjHd8PkCP?si=P3Z0vUVFQNKxgoFuzGHjuw","youtube":"https://youtu.be/yxNFMht7IlU","soundcloud":"https://soundcloud.com/bensomerville/taxintermission?in=bensomerville/sets/the-greenstone-ep","filePath":"audio/taxi.mp3","coverPath":"img/icons/greenstone.jpg","runtime":"1:46"},"concavescent":{"songid":"concavescent","songname":"Concavescent","albumid":"greenstone","album":"The Greenstone EP","albumpos":4,"year":2015,"instrumental":false,"spotify":"https://open.spotify.com/track/5Rbt0WLdrEiAjYTpa8DAXB?si=heaVkcikR8i5b2HfUQMUhw","youtube":"https://youtu.be/9dEORVSh-Wc","soundcloud":"https://soundcloud.com/bensomerville/concavescent?in=bensomerville/sets/the-greenstone-ep","filePath":"audio/concavescent.mp3","coverPath":"img/icons/greenstone.jpg","runtime":"3:52"},"tripwired":{"songid":"tripwired","songname":"Tripwired","albumid":"greenstone","album":"The Greenstone EP","albumpos":5,"year":2015,"instrumental":false,"spotify":"https://open.spotify.com/track/4pJRq1gaMJWhXWDCynZcty?si=NFWZHuWiREatY3R61iXAxg","youtube":"https://youtu.be/m_9hC8LaAOE","soundcloud":"https://soundcloud.com/bensomerville/tripwired?in=bensomerville/sets/the-greenstone-ep","filePath":"audio/tripwired.mp3","coverPath":"img/icons/greenstone.jpg","runtime":"5:39"},"endothermic":{"songid":"endothermic","songname":"Endothermic","albumid":"greenstone","album":"The Greenstone EP","albumpos":6,"year":2015,"instrumental":false,"spotify":"https://open.spotify.com/track/4DBcz16GHnxsevcAizwYqD?si=J3W9Ux73RXyFTiXTYiOR6A","youtube":"https://youtu.be/m_9hC8LaAOE","soundcloud":"https://soundcloud.com/bensomerville/endothermic?in=bensomerville/sets/the-greenstone-ep","filePath":"audio/endothermic.mp3","coverPath":"img/icons/greenstone.jpg","runtime":"3:26"},"cactusjuice":{"songid":"cactusjuice","songname":"Cactus Juice","albumid":"stainless","album":"Stainless Cactus","albumpos":1,"year":2015,"instrumental":true,"spotify":"","youtube":"","soundcloud":"","filePath":"audio/cactusjuice.mp3","coverPath":"img/icons/stainless.jpg","runtime":"1:50"},"frozenfloor":{"songid":"frozenfloor","songname":"On A Frozen Floor","albumid":"stainless","album":"Stainless Cactus","albumpos":2,"year":2015,"instrumental":true,"spotify":"","youtube":"","soundcloud":"","filePath":"audio/frozenfloor.mp3","coverPath":"img/icons/stainless.jpg","runtime":"3:28"},"trypnosis":{"songid":"trypnosis","songname":"Trypnosis","albumid":"stainless","album":"Stainless Cactus","albumpos":3,"year":2015,"instrumental":true,"spotify":"","youtube":"","soundcloud":"","filePath":"audio/trypnosis.mp3","coverPath":"img/icons/stainless.jpg","runtime":"2:07"},"rhythmic":{"songid":"rhythmic","songname":"Rhythmic Hums And Buzzes Of The Milky Way","albumid":"stainless","album":"Stainless Cactus","albumpos":4,"year":2015,"instrumental":true,"spotify":"","youtube":"","soundcloud":"","filePath":"audio/rhythmic.mp3","coverPath":"img/icons/stainless.jpg","runtime":"6:05"}}